tundri/__init__.py
tundri/cli.py
tundri/constants.py
tundri/core.py
tundri/inspector.py
tundri/objects.py
tundri/parser.py
tundri/utils.py
tundri-1.3.3.dist-info/METADATA
tundri-1.3.3.dist-info/WHEEL
tundri-1.3.3.dist-info/entry_points.txt
tundri-1.3.3.dist-info/RECORD
