Metadata-Version: 2.4
Name: tundri
Version: 1.3.3
Summary: Drop, create and alter Snowflake objects and set permissions with Permifrost
Project-URL: Homepage, https://github.com/Gemma-Analytics/tundri
Project-URL: Repository, https://github.com/Gemma-Analytics/tundri
Project-URL: Issues, https://github.com/Gemma-Analytics/tundri/issues
Author-email: Gemma Analytics <bijan.soltani@gemmaanalytics.com>
License: MIT
Keywords: database,ddl,permifrost,snowflake
Classifier: Development Status :: 4 - Beta
Classifier: Intended Audience :: Developers
Classifier: License :: OSI Approved :: MIT License
Classifier: Programming Language :: Python :: 3
Classifier: Programming Language :: Python :: 3.8
Classifier: Programming Language :: Python :: 3.9
Classifier: Programming Language :: Python :: 3.10
Classifier: Programming Language :: Python :: 3.11
Classifier: Programming Language :: Python :: 3.12
Requires-Python: >=3.8
Requires-Dist: gemma-permifrost
Requires-Dist: python-dotenv
Requires-Dist: pyyaml
Requires-Dist: rich
Requires-Dist: snowflake-connector-python
